neodantic/__init__.py
neodantic/__main__.py
neodantic/py.typed
neodantic-0.0.0.dist-info/entry_points.txt
neodantic-0.0.0.dist-info/LICENSE
neodantic-0.0.0.dist-info/WHEEL
neodantic-0.0.0.dist-info/METADATA
neodantic-0.0.0.dist-info/RECORD
