Metadata-Version: 2.1
Name: neodantic
Version: 0.0.0
Summary: Neodantic
Home-page: https://github.com/dekoza/neodantic
License: Apache-2.0
Author: Dominik Kozaczko
Author-email: dominik@kozaczko.info
Requires-Python: >=3.7,<4.0
Classifier: Development Status :: 1 - Planning
Classifier: License :: OSI Approved :: Apache Software License
Classifier: Programming Language :: Python :: 3
Classifier: Programming Language :: Python :: 3.7
Classifier: Programming Language :: Python :: 3.8
Classifier: Programming Language :: Python :: 3.9
Classifier: Programming Language :: Python :: 3.10
Requires-Dist: click (>=8.0.1)
Project-URL: Changelog, https://github.com/dekoza/neodantic/releases
Project-URL: Documentation, https://neodantic.readthedocs.io
Project-URL: Repository, https://github.com/dekoza/neodantic
